packageforadditionjenly/__init__.py
packageforaddition-0.1.0.dist-info/LICENCE.txt
packageforaddition-0.1.0.dist-info/METADATA
packageforaddition-0.1.0.dist-info/WHEEL
packageforaddition-0.1.0.dist-info/top_level.txt
packageforaddition-0.1.0.dist-info/RECORD
