Metadata-Version: 2.1
Name: packageforaddition
Version: 0.1.0
Summary: My first Python package
Home-page: UNKNOWN
Author: Ashik
Author-email: jenlyashik@gmail.com
License: MIT
Platform: UNKNOWN
License-File: LICENCE.txt
